Lab_10.srcs/sources_1/new/DFlipFlop.v
`timescale 1ns / 1ps

module DFlipFlop(
    input Data,
    input Clock,
    output reg Q,
    output notQ
    );

    initial begin
        Q <= 0;
    end
    
    always @ (posedge Clock) begin //on data or enable change from 0-1 this begin
        if(Clock)
            Q <= Data;
     end
        assign notQ = ~Q; //this doesnt cause problems as until Q is called for the first time it is a invalid state
          
endmodule

Lab_10.srcs/sources_1/new/JKFlipFlop.v
`timescale 1ns / 1ps

module JKFlipFlop(
    input J,K,
    input JKClock,
 
    wire JKData,
    wire JKQ,
    wire notJKQ
    );

    assign JKData = (J & ~JKQ) | (~K & JKQ);
    
        DFlipFlop DJK_init(
        .Data(JKData),
        .Clock(JKClock),
        .Q(JKQ),
        .notQ(notJKQ)
        );
endmodule

Lab_10.srcs/sources_1/new/TFlipFlop.v
`timescale 1ns / 1ps

module TFlipFlop(
    input T, TClock,
    
    wire TData,
    output TQ,
    output notTQ
    );
    
   JKFlipFlop JK_init(
     .J(T),     
     .K(T),     
     .JKClock(TClock),
     .JKQ(TQ),  
     .notJKQ(notTQ)
   );
  
endmodule

Lab_10.srcs/sources_1/new/top.v
`timescale 1ns / 1ps

module top(
input [15:0]sw,
input btnC,
output [15:0] led
    );
    
    //add module for D-FF with posedge
    DFlipFlop DFF_init(
    .Data(sw[0]),
    .Clock(btnC),
    .Q(led[0]),
    .notQ(led[1])
    );
    //add module for JK-FF
    JKFlipFlop JK_init(
        .J(sw[1]),
        .K(sw[2]),
        .JKClock(btnC),
        .JKQ(led[2]),
        .notJKQ(led[3])
        //.JKData(led[6]) debug and testing only
    );
    //add module for T-FF
    
    TFlipFlop T_init(
        .T(sw[3]),
        .TClock(btnC),
        .TQ(led[4]),
        .notTQ(led[5])
    );
endmodule

test.v
module test();
    reg [3:0] sw;
    reg btnC;
    wire [5:0] led;

    top uut(
        .sw(sw),
        .led(led),
        .btnC(btnC)
    );

    task automatic toggle_clock;
        begin
            #1 btnC = 1;
            #1 btnC = 0;
        end
    endtask

    task automatic set_check_dff(input D, input ExpectedQ);
        begin
            sw[0] = D;
            toggle_clock();
            if (led[0] != ExpectedQ || led[1] == ExpectedQ) begin
                $display("D FF test failed: expected Q = %b, ~Q = %b got %b | %b", ExpectedQ, ~ExpectedQ, led[0], led[1]);
                $finish;
            end
        end
    endtask

    task automatic set_check_jkff(input J, input K, input ExpectedQ);
        begin
            sw[1] = J;
            sw[2] = K;
            toggle_clock();
            //#1 //student added
            if (led[2] != ExpectedQ || led[3] == ExpectedQ) begin
                $display("JK FF test failed: expected Q = %b, ~Q = %b got %b | %b", ExpectedQ, ~ExpectedQ, led[2], led[3]);
                $finish;
            end
        end
    endtask

    task automatic set_check_tff(input T, input ExpectedQ);
        begin
            sw[3] = T;
            toggle_clock();
            if (led[4] != ExpectedQ || led[5] == ExpectedQ) begin
                $display("T FF test failed: expected Q = %b, ~Q = %b got %b | %b", ExpectedQ, ~ExpectedQ, led[4], led[5]);
                $finish;
            end
        end
    endtask

    initial begin
        $dumpvars(0,test);
        btnC = 0;
        sw = 4'b0;
        toggle_clock();
        
        set_check_dff(0, 0);
        set_check_dff(1, 1);

        set_check_jkff(0, 1, 0);
        set_check_jkff(0, 0, 0);
        set_check_jkff(1, 0, 1);
        set_check_jkff(0, 0, 1);
        set_check_jkff(1, 1, 0);
        set_check_jkff(1, 1, 1);

        set_check_tff(0, 0);
        set_check_tff(1, 1);
        set_check_tff(0, 1);
        set_check_tff(1, 0);
    
        $display("Test passed!!");
        $finish;
    end

endmodule

Lab_10.sim/sim_1/behav/xsim/dump.vcd
$date
   Thu Apr  3 12:49:21 2025
$end

$version
  2024.2.0
$end

$timescale
  1ps
$end

$scope module test $end
$var reg 4 ! sw [3:0] $end
$var reg 1 " btnC $end
$var wire 6 # led [5:0] $end
$scope module uut $end
$var wire 16 $ sw [15:0] $end
$var wire 1 % btnC $end
$var wire 16 & led [15:0] $end
$scope module DFF_init $end
$var wire 1 ' Data $end
$var wire 1 % Clock $end
$var reg 1 ( Q $end
$var wire 1 ) notQ $end
$upscope $end
$scope module JK_init $end
$var wire 1 * J $end
$var wire 1 + K $end
$var wire 1 % JKClock $end
$var wire 1 , JKData $end
$var wire 1 - JKQ $end
$var wire 1 . notJKQ $end
$scope module DJK_init $end
$var wire 1 , Data $end
$var wire 1 % Clock $end
$var reg 1 / Q $end
$var wire 1 . notQ $end
$upscope $end
$upscope $end
$scope module T_init $end
$var wire 1 0 T $end
$var wire 1 % TClock $end
$var wire 1 1 TData $end
$var wire 1 2 TQ $end
$var wire 1 3 notTQ $end
$scope module JK_init $end
$var wire 1 0 J $end
$var wire 1 0 K $end
$var wire 1 % JKClock $end
$var wire 1 4 JKData $end
$var wire 1 2 JKQ $end
$var wire 1 3 notJKQ $end
$scope module DJK_init $end
$var wire 1 4 Data $end
$var wire 1 % Clock $end
$var reg 1 5 Q $end
$var wire 1 3 notQ $end
$upscope $end
$upscope $end
$upscope $end
$upscope $end
$scope task toggle_clock $end
$upscope $end
$scope task set_check_dff $end
$upscope $end
$scope task set_check_jkff $end
$upscope $end
$scope task set_check_tff $end
$upscope $end
$upscope $end
$enddefinitions $end

#0
$dumpvars
b0 !
0"
b101010 #
bz0000 $
0%
bz101010 &
0'
0(
1)
0*
0+
0,
0-
1.
0/
00
z1
02
13
04
05
$end

#1000
1"
1%

#2000
0"
0%

#3000
1"
1%

#4000
b1 !
0"
bz0001 $
0%
1'
0*
0+
00

#5000
1"
b101001 #
1%
bz101001 &
1(
0)

#6000
b101 !
0"
bz0101 $
0%
1'
0*
1+
00

#7000
1"
1%

#8000
b1 !
0"
bz0001 $
0%
1'
0*
0+
00

#9000
1"
1%

#10000
b11 !
0"
bz0011 $
0%
1'
1*
0+
1,
00

#11000
1"
b100101 #
1%
bz100101 &
1-
0.
1/

#12000
b1 !
0"
bz0001 $
0%
1'
0*
0+
00

#13000
1"
1%

#14000
b111 !
0"
bz0111 $
0%
1'
1*
1+
0,
00

#15000
1"
b101001 #
1%
bz101001 &
1,
0-
1.
0/

#16000
0"
0%

#17000
1"
b100101 #
1%
bz100101 &
0,
1-
0.
1/

#18000
0"
0%

#19000
1"
b101001 #
1%
bz101001 &
1,
0-
1.
0/

#20000
b1111 !
0"
bz1111 $
0%
1'
1*
1+
10
14

#21000
1"
b10101 #
1%
bz010101 &
0,
1-
0.
1/
12
03
04
15

#22000
b111 !
0"
bz0111 $
0%
1'
1*
1+
00
14

#23000
1"
b11001 #
1%
bz011001 &
1,
0-
1.
0/

#24000
b1111 !
0"
bz1111 $
0%
1'
1*
1+
10
04

#25000
1"
b100101 #
1%
bz100101 &
0,
1-
0.
1/
02
13
14
05

#26000
0"
